grug/__init__.py
grug-0.0.0a1.dist-info/METADATA
grug-0.0.0a1.dist-info/WHEEL
grug-0.0.0a1.dist-info/top_level.txt
grug-0.0.0a1.dist-info/RECORD
